LICENSE
kumo/__init__.py
kumo/crawler.py
kumo/edge.py
kumo/errors.py
kumo/storage/__init__.py
kumo/storage/funcs.py
kumo/storage/memory.py
kumo/types.py
kumo/utils.py
kumo_py-0.1.0.dist-info/LICENSE
kumo_py-0.1.0.dist-info/WHEEL
kumo_py-0.1.0.dist-info/METADATA
kumo_py-0.1.0.dist-info/RECORD
